oubliette/__init__.py
oubliette/alises.py
oubliette/attributes.py
oubliette/exceptions.py
oubliette/utils.py
oubliette/areas/__init__.py
oubliette/areas/town.py
oubliette/core/__init__.py
oubliette/core/events.py
oubliette/core/game.py
oubliette/core/intents.py
oubliette/core/session.py
oubliette/core/interfaces/__init__.py
oubliette/core/interfaces/context.py
oubliette/core/interfaces/prompt.py
oubliette/core/interfaces/target_stack.py
oubliette/core/interfaces/term.py
oubliette/core/navigation/__init__.py
oubliette/core/navigation/areas.py
oubliette/core/navigation/base.py
oubliette/core/navigation/directions.py
oubliette/core/navigation/junctions.py
oubliette/core/navigation/portals.py
oubliette/entities/__init__.py
oubliette/entities/base.py
oubliette/entities/menu.py
oubliette/entities/npcs.py
oubliette/entities/player.py
oubliette/items/__init__.py
oubliette/items/base.py
oubliette/items/equipment.py
oubliette/items/inventory.py
oubliette/items/minerals.py
oubliette/items/misc.py
oubliette/items/weapons.py
oubliette/materials/__init__.py
oubliette/materials/materials.py
oubliette/materials/properties.py
oubliette-0.0.1.dist-info/METADATA
oubliette-0.0.1.dist-info/WHEEL
oubliette-0.0.1.dist-info/top_level.txt
oubliette-0.0.1.dist-info/RECORD
