Metadata-Version: 2.1
Name: oubliette
Version: 0.0.1
Summary: Dungeon crawl
Home-page: https://gitlab.com/kodiaknitro/oubliette
Author: Kodiak Nitro
Author-email: jon@jonathanferretti.com
License: UNKNOWN
Platform: UNKNOWN
Classifier: Development Status :: 1 - Planning
Requires-Python: >=3.6
